spaghetr/__init__.py
spaghetr/client.py
spaghetr/compile_pb.py
spaghetr/server.py
spaghetr/util.py
spaghetr/version.py
spaghetr/protos/__init__.py
spaghetr/protos/basic_subproc.proto
spaghetr/protos/basic_subproc_pb2.py
spaghetr/protos/basic_subproc_pb2_grpc.py
spaghetr/protos/status.proto
spaghetr/protos/status_pb2.py
spaghetr/protos/status_pb2_grpc.py
spaghetr-0.0.5.dist-info/METADATA
spaghetr-0.0.5.dist-info/WHEEL
spaghetr-0.0.5.dist-info/top_level.txt
spaghetr-0.0.5.dist-info/RECORD
